easy_speak/__init__.py
easy_speak/core.py
easy_speak-0.1.1.dist-info/LICENSE
easy_speak-0.1.1.dist-info/METADATA
easy_speak-0.1.1.dist-info/WHEEL
easy_speak-0.1.1.dist-info/top_level.txt
easy_speak-0.1.1.dist-info/RECORD
